pickleassem.py
pickleassem-1.1.0.dist-info/LICENSE.txt
pickleassem-1.1.0.dist-info/METADATA
pickleassem-1.1.0.dist-info/WHEEL
pickleassem-1.1.0.dist-info/top_level.txt
pickleassem-1.1.0.dist-info/RECORD
