Metadata-Version: 2.1
Name: pickleassem
Version: 1.1.0
Summary: A simple pickle assembler to make handcrafting pickle bytecode easier.
Home-page: https://github.com/gousaiyang/pickleassem
Author: Saiyang Gou
Author-email: gousaiyang223@gmail.com
License: MIT
Keywords: pickle assembler handcraft bytecode security exploit ctf
Platform: UNKNOWN
Classifier: Development Status :: 5 - Production/Stable
Classifier: Intended Audience :: Developers
Classifier: Intended Audience :: Information Technology
Classifier: License :: OSI Approved :: MIT License
Classifier: Operating System :: OS Independent
Classifier: Programming Language :: Python :: 3 :: Only
Classifier: Topic :: Security
Classifier: Topic :: Software Development :: Assemblers
Classifier: Topic :: Utilities
Requires-Python: >=3.4
Requires-Dist: typing-extensions (>=3.7.2)
Requires-Dist: typing ; python_version < "3.5"
